pyslot/__init__.py
pyslot/signal.py
pyslot/thread_safe_signal.py
pyslot-2.0.1.dist-info/DESCRIPTION.rst
pyslot-2.0.1.dist-info/METADATA
pyslot-2.0.1.dist-info/RECORD
pyslot-2.0.1.dist-info/WHEEL
pyslot-2.0.1.dist-info/metadata.json
pyslot-2.0.1.dist-info/top_level.txt
