Metadata-Version: 2.0
Name: pyslot
Version: 2.0.1
Summary: A dead-simple signal/slot implementation for Python.
Home-page: http://ereOn.github.io/pyslot
Author: Julien Kauffmann
Author-email: julien.kauffmann@freelan.org
License: UNKNOWN
Platform: UNKNOWN
Classifier: Intended Audience :: Developers
Classifier: Operating System :: OS Independent
Classifier: Programming Language :: Python :: 2
Classifier: Programming Language :: Python :: 2.7
Classifier: Programming Language :: Python :: 3
Classifier: Programming Language :: Python :: 3.3
Classifier: Programming Language :: Python :: 3.4
Classifier: Programming Language :: Python :: 3.5
Classifier: Topic :: Software Development
Classifier: Topic :: Software Development :: Libraries :: Python Modules
Classifier: Development Status :: 5 - Production/Stable
Requires-Dist: six (>=1.10.0,<2.0.0)
